testtrace.py
testtrace-0.1.dist-info/RECORD
testtrace-0.1.dist-info/metadata.json
testtrace-0.1.dist-info/top_level.txt
testtrace-0.1.dist-info/DESCRIPTION.rst
testtrace-0.1.dist-info/WHEEL
testtrace-0.1.dist-info/METADATA
testtrace-0.1.dist-info/zip-safe
