Metadata-Version: 2.0
Name: testtrace
Version: 0.1
Summary: Python TestResult subclass that does code tracing
Home-page: https://launchpad.net/testtrace/
Author: Zygmunt Krynicki
Author-email: zygmunt.krynicki@canonical.com
License: GPLv3
Platform: POSIX
Classifier: Development Status :: 5 - Production/Stable
Classifier: Intended Audience :: Developers
Classifier: License :: OSI Approved :: GNU General Public License v3 (GPLv3)
Classifier: Natural Language :: English
Classifier: Programming Language :: Python :: 2
Classifier: Programming Language :: Python :: 3
Classifier: Topic :: Software Development :: Libraries :: Python Modules
Classifier: Topic :: Software Development :: Testing
